projinit/__init__.py
projinit/main.py
structinit-1.0.1.dist-info/licenses/LICENSE
structinit-1.0.1.dist-info/METADATA
structinit-1.0.1.dist-info/WHEEL
structinit-1.0.1.dist-info/entry_points.txt
structinit-1.0.1.dist-info/top_level.txt
structinit-1.0.1.dist-info/RECORD
