Metadata-Version: 2.4
Name: structinit
Version: 1.0.1
Summary: 🛠️ Generate full project structures from markdown blueprints.
Home-page: https://github.com/srijanbahal/Projinit
Author: Srijan
Author-email: srijanbahal.work@example.com
License: MIT
Keywords: project scaffolding,markdown,CLI,automation
Classifier: Programming Language :: Python :: 3
Classifier: License :: OSI Approved :: MIT License
Classifier: Operating System :: OS Independent
Requires-Python: >=3.6
License-File: LICENSE
Requires-Dist: requests
Dynamic: author
Dynamic: author-email
Dynamic: classifier
Dynamic: description
Dynamic: description-content-type
Dynamic: home-page
Dynamic: keywords
Dynamic: license
Dynamic: license-file
Dynamic: requires-dist
Dynamic: requires-python
Dynamic: summary
